setup.py
tdu_distributions/Binomialdistribution.py
tdu_distributions/Gaussiandistribution.py
tdu_distributions/Generaldistribution.py
tdu_distributions/__init__.py
tdu_distributions.egg-info/PKG-INFO
tdu_distributions.egg-info/SOURCES.txt
tdu_distributions.egg-info/dependency_links.txt
tdu_distributions.egg-info/not-zip-safe
tdu_distributions.egg-info/top_level.txt